tmdb/__init__.py
tmdb/api_key.py
tmdb/const.py
tmdb/db.py
tmdb/movie.py
tmdb/person.py
tmdb/tmdb.py
my_tmdb-0.0.2.dist-info/METADATA
my_tmdb-0.0.2.dist-info/WHEEL
my_tmdb-0.0.2.dist-info/top_level.txt
my_tmdb-0.0.2.dist-info/zip-safe
my_tmdb-0.0.2.dist-info/RECORD
